README
setup.cfg
setup.py
ifconfigpy/__init__.py
ifconfigpy/base.py
ifconfigpy/iface.py
ifconfigpy.egg-info/PKG-INFO
ifconfigpy.egg-info/SOURCES.txt
ifconfigpy.egg-info/dependency_links.txt
ifconfigpy.egg-info/top_level.txt
ifconfigpy/driver/__init__.py
ifconfigpy/driver/_freebsd.c
ifconfigpy/driver/freebsd.py