Metadata-Version: 1.1
Name: ifconfigpy
Version: 0.0.1.devr11
Summary: ifconfigpy is a python library to manipulate interfaces like ifconfig
Home-page: http://bitbucket.org/williambr/ifconfigpy
Author: William Grzybowski
Author-email: william88@gmail.com
License: BSD
Keywords: ifconfig
Platform: any
Classifier: Development Status :: 1 - Planning
Classifier: Intended Audience :: Developers
Classifier: License :: OSI Approved :: BSD License
Classifier: Operating System :: POSIX :: BSD :: FreeBSD
Classifier: Programming Language :: Python
